pyquats/__init__.py
pyquats/numpyquats.py
pyquats/qmath.py
pyquats/qtools.py
pyquats/quats.py
pyquats/tests/__init__.py
pyquats/tests/test_circle.py
pyquats/tests/test_numpyquats.py
pyquats/tests/test_qmath.py
pyquats/tests/test_qtools.py
pyquats/tests/test_quats.py
pyquats/tests/test_rotation1.py
pyquats/tests/test_rotation2.py
pyquats/tests/test_rotation3.py
pyquats/tests/test_rotation4.py
pyquats/tests/test_rotation5.py
pyquats/tests/timeit_exp.py
pyquats/tests/timeit_quat.py
pyquats/tests/timeit_sin.py
pyquats-1.1.0.dist-info/LICENSE
pyquats-1.1.0.dist-info/METADATA
pyquats-1.1.0.dist-info/WHEEL
pyquats-1.1.0.dist-info/top_level.txt
pyquats-1.1.0.dist-info/RECORD
