Metadata-Version: 2.1
Name: pyquats
Version: 1.1.0
Summary: Python implementation of quaternions
Home-page: https://github.com/ufkapano/pyquats
Author: Andrzej Kapanowski
Author-email: andrzej.kapanowski@uj.edu.pl
Classifier: Programming Language :: Python :: 3
Classifier: License :: OSI Approved :: BSD License
Classifier: Operating System :: OS Independent
Classifier: Topic :: Education
Classifier: Topic :: Scientific/Engineering
Requires-Python: >=3.7
License-File: LICENSE
Requires-Dist: numpy
